django_nitro-0.7.0.dist-info/licenses/LICENSE
nitro/__init__.py
nitro/api.py
nitro/apps.py
nitro/base.py
nitro/cache.py
nitro/conf.py
nitro/debug_toolbar_panel.py
nitro/list.py
nitro/registry.py
nitro/security.py
nitro/tests.py
nitro/tests_real_world.py
nitro/utils.py
nitro/views.py
nitro/static/nitro/nitro.css
nitro/static/nitro/nitro.js
nitro/templates/nitro/component_page.html
nitro/templates/nitro/debug_toolbar_panel.html
nitro/templates/nitro/components/expandable_panel.html
nitro/templates/nitro/components/searchable_dropdown.html
nitro/templates/nitro/components/slideover.html
nitro/templates/nitro/fields/checkbox.html
nitro/templates/nitro/fields/dynamic_select.html
nitro/templates/nitro/fields/input.html
nitro/templates/nitro/fields/phone.html
nitro/templates/nitro/fields/select.html
nitro/templates/nitro/fields/textarea.html
nitro/templatetags/__init__.py
nitro/templatetags/nitro_components.py
nitro/templatetags/nitro_tags.py
nitro/templatetags/nitro_zero.py
django_nitro-0.7.0.dist-info/METADATA
django_nitro-0.7.0.dist-info/WHEEL
django_nitro-0.7.0.dist-info/top_level.txt
django_nitro-0.7.0.dist-info/RECORD
