Metadata-Version: 2.4
Name: django-nitro
Version: 0.7.0
Summary: Reactive Django components using AlpineJS and Django Ninja
Author-email: Jearel Alcantara <jeasoft@gmail.com>
License: MIT
Project-URL: Homepage, https://github.com/django-nitro/django-nitro
Project-URL: Documentation, https://github.com/django-nitro/django-nitro#readme
Project-URL: Repository, https://github.com/django-nitro/django-nitro
Project-URL: Issues, https://github.com/django-nitro/django-nitro/issues
Keywords: django,alpinejs,reactive,components,django-ninja
Classifier: Development Status :: 4 - Beta
Classifier: Environment :: Web Environment
Classifier: Framework :: Django
Classifier: Framework :: Django :: 5.2
Classifier: Framework :: Django :: 6.0
Classifier: Intended Audience :: Developers
Classifier: License :: OSI Approved :: MIT License
Classifier: Operating System :: OS Independent
Classifier: Programming Language :: Python
Classifier: Programming Language :: Python :: 3
Classifier: Programming Language :: Python :: 3.12
Classifier: Programming Language :: Python :: 3.13
Classifier: Programming Language :: Python :: 3.14
Classifier: Topic :: Internet :: WWW/HTTP
Classifier: Topic :: Internet :: WWW/HTTP :: Dynamic Content
Requires-Python: >=3.12
License-File: LICENSE
Requires-Dist: Django>=5.2
Requires-Dist: django-ninja>=1.4.0
Requires-Dist: pydantic>=2.0.0
Requires-Dist: email-validator>=2.0.0
Provides-Extra: django52
Requires-Dist: django-template-partials>=24.4; extra == "django52"
Provides-Extra: dev
Requires-Dist: pytest>=7.0.0; extra == "dev"
Requires-Dist: pytest-django>=4.5.0; extra == "dev"
Requires-Dist: pytest-cov>=4.0.0; extra == "dev"
Requires-Dist: ruff>=0.8.0; extra == "dev"
Requires-Dist: mypy>=1.0.0; extra == "dev"
Requires-Dist: django-stubs>=4.0.0; extra == "dev"
Dynamic: license-file
